[{"id":"madas_iygb_c4_l_q1_exact_inputs","source_pdf":"MadAsMaths papers/c4_l.pdf","question":"q1","part":"all","verdict":"partial","review_basis":"manual page-image review: c4_l questions 5 pages, marks 1 pages, solutions 6 pages","inputs":[{"module":"algebra","input":"method=numeric,4/3","mark_scheme_working":["volume"],"expected_output_markers":["1.33333333333"]}],"expected_final":["volume"],"unsupported_reason":"setup is manual"},{"id":"madas_iygb_c4_l_q2_exact_inputs","source_pdf":"MadAsMaths papers/c4_l.pdf","question":"q2","part":"a-b","verdict":"testable","review_basis":"manual page-image review: c4_l questions 5 pages, marks 1 pages, solutions 6 pages","inputs":[{"module":"algebra","input":"method=numeric,16/3","mark_scheme_working":["integral"],"expected_output_markers":["5.33333333333"]}],"expected_final":["area=16/3"]},{"id":"madas_iygb_c4_l_q3_exact_inputs","source_pdf":"MadAsMaths papers/c4_l.pdf","question":"q3","part":"a-c","verdict":"partial","review_basis":"manual page-image review: c4_l questions 5 pages, marks 1 pages, solutions 6 pages","inputs":[{"module":"algebra","input":"method=numeric,3","mark_scheme_working":["constant"],"expected_output_markers":["3"]}],"expected_final":["DE"],"unsupported_reason":"setup is manual"},{"id":"madas_iygb_c4_l_q4_exact_inputs","source_pdf":"MadAsMaths papers/c4_l.pdf","question":"q4","part":"a-b","verdict":"partial","review_basis":"manual page-image review: c4_l questions 5 pages, marks 1 pages, solutions 6 pages","inputs":[{"module":"algebra","input":"method=numeric,pi/6","mark_scheme_working":["trig"],"expected_output_markers":["0.523598775598"]}],"expected_final":["integration"],"unsupported_reason":"substitution is manual"},{"id":"madas_iygb_c4_l_q5_exact_inputs","source_pdf":"MadAsMaths papers/c4_l.pdf","question":"q5","part":"a-d","verdict":"testable","review_basis":"manual page-image review: c4_l questions 5 pages, marks 1 pages, solutions 6 pages","inputs":[{"module":"algebra","input":"method=numeric,ln(5)","mark_scheme_working":["log"],"expected_output_markers":["1.60943791243"]}],"expected_final":["x=5"]},{"id":"madas_iygb_c4_l_complete_source_marker","source_pdf":"MadAsMaths papers/c4_l.pdf","coverage":"complete","question":"all_questions","part":"source-complete","verdict":"skip","review_basis":"manual page-image review: all 5 question pages, 1 mark pages and 6 worked-solution pages","unsupported_reason":"source complete marker; executable exact calculator inputs are recorded in c4_l rows above, while diagram/proof/branch judgements are manual notes"}]
